README.md
setup.cfg
setup.py
eupy/__init__.py
eupy.egg-info/PKG-INFO
eupy.egg-info/SOURCES.txt
eupy.egg-info/dependency_links.txt
eupy.egg-info/requires.txt
eupy.egg-info/top_level.txt
eupy/hermes/__init__.py
eupy/hermes/client.py
eupy/mrcrawley/AZspider.py
eupy/mrcrawley/__init__.py
eupy/mrcrawley/crawler.py
eupy/mrcrawley/test.py
eupy/native/__init__.py
eupy/native/logger.py
eupy/native/plotter.py
eupy/native/profiler.py
eupy/native/shell.py