Metadata-Version: 1.1
Name: eupy
Version: 1.0.15
Summary: Python set of utils and libraries
Home-page: http://github.com/fivosts/eupy
Author: Foivos Tsimpourlas
Author-email: fivos_ts@hotmail.com
License: MIT
Platform: UNKNOWN
Classifier: Programming Language :: Python :: 3.7
